myfuncs.py
setup_name-0.0.1.dist-info/METADATA
setup_name-0.0.1.dist-info/WHEEL
setup_name-0.0.1.dist-info/top_level.txt
setup_name-0.0.1.dist-info/RECORD
