Metadata-Version: 2.1
Name: setup-name
Version: 0.0.1
Summary: Myfuncolandia
Home-page: UNKNOWN
License: UNKNOWN
Platform: UNKNOWN
